[
    {
        "type": "heading-one",
        "children": [
            {
                "text": "Title"
            }
        ]
    },
    {
        "type": "heading-two",
        "children": [
            {
                "text": "Secondary title"
            }
        ]
    },
    {
        "type": "paragraph",
        "children": [
            {
                "text": "Pharagraph"
            }
        ]
    },
    {
        "type": "numbered-list",
        "children": [
            {
                "type": "list-item",
                "children": [
                    {
                        "text": "list",
                        "bold": true
                    }
                ]
            },
            {
                "type": "list-item",
                "children": [
                    {
                        "text": "list"
                    }
                ]
            },
            {
                "type": "list-item",
                "children": [
                    {
                        "text": "list"
                    }
                ]
            }
        ]
    },
    {
        "type": "bulleted-list",
        "children": [
            {
                "type": "list-item",
                "children": [
                    {
                        "text": "list"
                    }
                ]
            },
            {
                "type": "list-item",
                "children": [
                    {
                        "text": "list"
                    }
                ]
            },
            {
                "type": "list-item",
                "children": [
                    {
                        "text": "list"
                    }
                ]
            }
        ]
    },
    {
        "type": "paragraph",
        "children": [
            {
                "text": "left"
            }
        ]
    },
    {
        "type": "paragraph",
        "children": [
            {
                "text": "right"
            }
        ],
        "align": "right"
    },
    {
        "type": "paragraph",
        "children": [
            {
                "text": "center"
            }
        ],
        "align": "center"
    },
    {
        "type": "paragraph",
        "children": [
            {
                "text": "justify "
            }
        ],
        "align": "justify"
    },
    {
        "type": "paragraph",
        "align": "justify",
        "children": [
            {
                "text": "Lorem ipsum dolor sit amet, consectetur adipiscing elit. Etiam semper diam at erat pulvinar, at pulvinar felis blandit. Vestibulum volutpat tellus diam, consequat gravida libero rhoncus ut. Lorem ipsum dolor sit amet, consectetur adipiscing elit. Etiam semper diam at erat pulvinar, at pulvinar felis blandit. Vestibulum volutpat tellus diam, consequat gravida libero rhoncus ut."
            }
        ]
    },
    {
        "type": "paragraph",
        "children": [
            {
                "text": "code",
                "code": true
            }
        ]
    },
    {
        "type": "paragraph",
        "children": [
            {
                "text": "export default function NoSSR({ children }) {",
                "code": true
            }
        ]
    },
    {
        "type": "paragraph",
        "children": [
            {
                "text": "    const [ok, setOk] = React.useState(false);",
                "code": true
            }
        ]
    },
    {
        "type": "paragraph",
        "children": [
            {
                "text": "    React.useEffect(() => {",
                "code": true
            }
        ]
    },
    {
        "type": "paragraph",
        "children": [
            {
                "text": "        setOk(true);",
                "code": true
            }
        ]
    },
    {
        "type": "paragraph",
        "children": [
            {
                "text": "    }, [])",
                "code": true
            }
        ]
    },
    {
        "type": "paragraph",
        "children": [
            {
                "text": "    return ok && children;",
                "code": true
            }
        ]
    },
    {
        "type": "paragraph",
        "children": [
            {
                "text": "}",
                "code": true
            }
        ]
    },
    {
        "type": "block-quote",
        "children": [
            {
                "text": "quote"
            }
        ]
    },
    {
        "type": "paragraph",
        "children": [
            {
                "text": "bold",
                "bold": true
            }
        ]
    },
    {
        "type": "paragraph",
        "children": [
            {
                "text": "italic",
                "italic": true
            }
        ]
    },
    {
        "type": "paragraph",
        "children": [
            {
                "text": "underliIne",
                "underline": true
            }
        ]
    },
    {
        "type": "image",
        "url": "https://letsenhance.io/static/8f5e523ee6b2479e26ecc91b9c25261e/1015f/MainAfter.jpg",
        "children": [
            {
                "text": ""
            }
        ]
    },
    {
        "type": "paragraph",
        "children": [
            {
                "text": ""
            }
        ]
    },
    {
        "type": "image",
        "url": "https://s3-eu-west-1.amazonaws.com/blog-ecotree/blog/0001/01/ad46dbb447cd0e9a6aeecd64cc2bd332b0cbcb79.jpeg",
        "children": [
            {
                "text": ""
            }
        ]
    },
    {
        "type": "paragraph",
        "children": [
            {
                "text": ""
            }
        ]
    },
    {
        "type": "paragraph",
        "children": [
            {
                "text": ""
            }
        ]
    },
    {
        "type": "image",
        "url": "https://dfstudio-d420.kxcdn.com/wordpress/wp-content/uploads/2019/06/digital_camera_photo-1080x675.jpg",
        "children": [
            {
                "text": ""
            }
        ]
    },
    {
        "type": "paragraph",
        "children": [
            {
                "text": ""
            }
        ]
    },
    {
        "type": "paragraph",
        "children": [
            {
                "text": ""
            }
        ]
    }
]